version/__init__.py
version/base.py
version/exceptions.py
version/command/__init__.py
version/command/__main__.py
version/command/case.py
version/core/__init__.py
version/core/utils.py
version/expression/__init__.py
version/expression/base.py
version/expression/base_method.py
version/expression/c_version_expression.py
version/expression/cargo_version_expression.py
version/expression/cocoapods_version_expression.py
version/expression/composer_version_expression.py
version/expression/go_version_expression.py
version/expression/hex_version_expression.py
version/expression/linux_version_expression.py
version/expression/maven_version_expression.py
version/expression/npm_version_expression.py
version/expression/nuget_version_expression.py
version/expression/nvd_version_expression.py
version/expression/other_version_expression.py
version/expression/pip_version_expression.py
version/expression/ruby_version_expression.py
version/expression/snyk_version_expression.py
version/version_base/__init__.py
version/version_base/base_item.py
version/version_base/base_version.py
version/version_base/common_method.py
version/version_base/composer_version.py
version/version_base/go_version.py
version/version_base/linux_version.py
version/version_base/lj_version.py
version/version_base/maven_version.py
version/version_base/npm_version.py
version/version_base/snyk_version.py
common_version-0.0.4.dist-info/LICENSE
common_version-0.0.4.dist-info/METADATA
common_version-0.0.4.dist-info/WHEEL
common_version-0.0.4.dist-info/entry_points.txt
common_version-0.0.4.dist-info/top_level.txt
common_version-0.0.4.dist-info/RECORD
